<annotation>
    <folder>VOC2007</folder>
    <filename>AL_00055.JPG</filename>
    <size>
        <width>800</width>
        <height>1160</height>
        <depth>3</depth>
    </size>
    <object>
        <name>l_faster</name>
        <pose>Unspecified</pose>
        <truncated>0</truncated>
        <difficult>0</difficult>
        <bndbox>
            <xmin>265</xmin>
            <ymin>311</ymin>
            <xmax>351</xmax>
            <ymax>430</ymax>
        </bndbox>
    </object>
    <object>
        <name>l_faster</name>
        <pose>Unspecified</pose>
        <truncated>0</truncated>
        <difficult>0</difficult>
        <bndbox>
            <xmin>266</xmin>
            <ymin>684</ymin>
            <xmax>352</xmax>
            <ymax>807</ymax>
        </bndbox>
    </object>
    <object>
        <name>r_faster</name>
        <pose>Unspecified</pose>
        <truncated>0</truncated>
        <difficult>0</difficult>
        <bndbox>
            <xmin>411</xmin>
            <ymin>310</ymin>
            <xmax>490</xmax>
            <ymax>421</ymax>
        </bndbox>
    </object>
    <object>
        <name>r_faster</name>
        <pose>Unspecified</pose>
        <truncated>0</truncated>
        <difficult>0</difficult>
        <bndbox>
            <xmin>413</xmin>
            <ymin>683</ymin>
            <xmax>491</xmax>
            <ymax>794</ymax>
        </bndbox>
    </object>
</annotation>