<annotation>
    <folder>VOC2007</folder>
    <filename>AR_00419.JPG</filename>
    <size>
        <width>800</width>
        <height>1160</height>
        <depth>3</depth>
    </size>
    <object>
        <name>l_faster</name>
        <pose>Unspecified</pose>
        <truncated>0</truncated>
        <difficult>0</difficult>
        <bndbox>
            <xmin>300</xmin>
            <ymin>363</ymin>
            <xmax>381</xmax>
            <ymax>474</ymax>
        </bndbox>
    </object>
    <object>
        <name>l_faster</name>
        <pose>Unspecified</pose>
        <truncated>0</truncated>
        <difficult>0</difficult>
        <bndbox>
            <xmin>301</xmin>
            <ymin>738</ymin>
            <xmax>383</xmax>
            <ymax>850</ymax>
        </bndbox>
    </object>
    <object>
        <name>r_faster</name>
        <pose>Unspecified</pose>
        <truncated>0</truncated>
        <difficult>0</difficult>
        <bndbox>
            <xmin>444</xmin>
            <ymin>733</ymin>
            <xmax>527</xmax>
            <ymax>844</ymax>
        </bndbox>
    </object>
    <object>
        <name>r_faster</name>
        <pose>Unspecified</pose>
        <truncated>0</truncated>
        <difficult>0</difficult>
        <bndbox>
            <xmin>444</xmin>
            <ymin>355</ymin>
            <xmax>527</xmax>
            <ymax>469</ymax>
        </bndbox>
    </object>
</annotation>