<annotation>
    <folder>VOC2007</folder>
    <filename>AR_00011.JPG</filename>
    <size>
        <width>800</width>
        <height>1160</height>
        <depth>3</depth>
    </size>
    <object>
        <name>l_faster</name>
        <pose>Unspecified</pose>
        <truncated>0</truncated>
        <difficult>0</difficult>
        <bndbox>
            <xmin>300</xmin>
            <ymin>751</ymin>
            <xmax>381</xmax>
            <ymax>866</ymax>
        </bndbox>
    </object>
    <object>
        <name>l_faster</name>
        <pose>Unspecified</pose>
        <truncated>0</truncated>
        <difficult>0</difficult>
        <bndbox>
            <xmin>300</xmin>
            <ymin>373</ymin>
            <xmax>383</xmax>
            <ymax>488</ymax>
        </bndbox>
    </object>
    <object>
        <name>l_faster</name>
        <pose>Unspecified</pose>
        <truncated>0</truncated>
        <difficult>0</difficult>
        <bndbox>
            <xmin>301</xmin>
            <ymin>1</ymin>
            <xmax>383</xmax>
            <ymax>115</ymax>
        </bndbox>
    </object>
    <object>
        <name>r_faster</name>
        <pose>Unspecified</pose>
        <truncated>0</truncated>
        <difficult>0</difficult>
        <bndbox>
            <xmin>443</xmin>
            <ymin>369</ymin>
            <xmax>527</xmax>
            <ymax>478</ymax>
        </bndbox>
    </object>
    <object>
        <name>r_faster</name>
        <pose>Unspecified</pose>
        <truncated>0</truncated>
        <difficult>0</difficult>
        <bndbox>
            <xmin>444</xmin>
            <ymin>742</ymin>
            <xmax>525</xmax>
            <ymax>854</ymax>
        </bndbox>
    </object>
</annotation>