<annotation>
    <folder>VOC2007</folder>
    <filename>AR_00493.JPG</filename>
    <size>
        <width>800</width>
        <height>1160</height>
        <depth>3</depth>
    </size>
    <object>
        <name>l_faster</name>
        <pose>Unspecified</pose>
        <truncated>0</truncated>
        <difficult>0</difficult>
        <bndbox>
            <xmin>301</xmin>
            <ymin>283</ymin>
            <xmax>384</xmax>
            <ymax>395</ymax>
        </bndbox>
    </object>
    <object>
        <name>l_faster</name>
        <pose>Unspecified</pose>
        <truncated>0</truncated>
        <difficult>0</difficult>
        <bndbox>
            <xmin>300</xmin>
            <ymin>656</ymin>
            <xmax>383</xmax>
            <ymax>769</ymax>
        </bndbox>
    </object>
    <object>
        <name>l_faster</name>
        <pose>Unspecified</pose>
        <truncated>0</truncated>
        <difficult>0</difficult>
        <bndbox>
            <xmin>301</xmin>
            <ymin>1030</ymin>
            <xmax>381</xmax>
            <ymax>1142</ymax>
        </bndbox>
    </object>
    <object>
        <name>r_faster</name>
        <pose>Unspecified</pose>
        <truncated>0</truncated>
        <difficult>0</difficult>
        <bndbox>
            <xmin>444</xmin>
            <ymin>277</ymin>
            <xmax>526</xmax>
            <ymax>388</ymax>
        </bndbox>
    </object>
    <object>
        <name>r_faster</name>
        <pose>Unspecified</pose>
        <truncated>0</truncated>
        <difficult>0</difficult>
        <bndbox>
            <xmin>443</xmin>
            <ymin>649</ymin>
            <xmax>525</xmax>
            <ymax>761</ymax>
        </bndbox>
    </object>
    <object>
        <name>r_faster</name>
        <pose>Unspecified</pose>
        <truncated>0</truncated>
        <difficult>0</difficult>
        <bndbox>
            <xmin>444</xmin>
            <ymin>1023</ymin>
            <xmax>528</xmax>
            <ymax>1135</ymax>
        </bndbox>
    </object>
</annotation>