<annotation>
    <folder>VOC2007</folder>
    <filename>AR_00547.JPG</filename>
    <size>
        <width>800</width>
        <height>1160</height>
        <depth>3</depth>
    </size>
    <object>
        <name>l_faster</name>
        <pose>Unspecified</pose>
        <truncated>0</truncated>
        <difficult>0</difficult>
        <bndbox>
            <xmin>301</xmin>
            <ymin>1033</ymin>
            <xmax>382</xmax>
            <ymax>1142</ymax>
        </bndbox>
    </object>
    <object>
        <name>l_faster</name>
        <pose>Unspecified</pose>
        <truncated>0</truncated>
        <difficult>0</difficult>
        <bndbox>
            <xmin>300</xmin>
            <ymin>658</ymin>
            <xmax>381</xmax>
            <ymax>770</ymax>
        </bndbox>
    </object>
    <object>
        <name>l_faster</name>
        <pose>Unspecified</pose>
        <truncated>0</truncated>
        <difficult>0</difficult>
        <bndbox>
            <xmin>298</xmin>
            <ymin>282</ymin>
            <xmax>380</xmax>
            <ymax>394</ymax>
        </bndbox>
    </object>
    <object>
        <name>r_faster</name>
        <pose>Unspecified</pose>
        <truncated>0</truncated>
        <difficult>0</difficult>
        <bndbox>
            <xmin>443</xmin>
            <ymin>276</ymin>
            <xmax>526</xmax>
            <ymax>390</ymax>
        </bndbox>
    </object>
    <object>
        <name>r_faster</name>
        <pose>Unspecified</pose>
        <truncated>0</truncated>
        <difficult>0</difficult>
        <bndbox>
            <xmin>444</xmin>
            <ymin>652</ymin>
            <xmax>528</xmax>
            <ymax>765</ymax>
        </bndbox>
    </object>
    <object>
        <name>r_faster</name>
        <pose>Unspecified</pose>
        <truncated>0</truncated>
        <difficult>0</difficult>
        <bndbox>
            <xmin>443</xmin>
            <ymin>1025</ymin>
            <xmax>526</xmax>
            <ymax>1137</ymax>
        </bndbox>
    </object>
</annotation>